MANIFEST.in
README.rst
setup.py
decent_tools.egg-info/PKG-INFO
decent_tools.egg-info/SOURCES.txt
decent_tools.egg-info/dependency_links.txt
decent_tools.egg-info/entry_points.txt
decent_tools.egg-info/not-zip-safe
decent_tools.egg-info/pbr.json
decent_tools.egg-info/requires.txt
decent_tools.egg-info/top_level.txt
dn/__init__.py
dn/bsl.py
dn/lusb/__init__.py
dn/lusb/common.py
dn/lusb/linux.py
dn/lusb/macosx.py
dn/tc65i/__init__.py
dn/tc65i/__main__.py
dn/tc65i/at.py
dn/tc65i/obex.py