Metadata-Version: 1.1
Name: decent-tools
Version: 0.2.6
Summary: decentnode tools
Home-page: http://www.decentlab.com
Author: xawirq
Author-email: xawirq@gmail.com
License: Apache License 2.0
Platform: UNKNOWN
Classifier: Programming Language :: Python :: 2.7
Classifier: Topic :: System :: Systems Administration
